AUTHORS
LICENSE
MANIFEST.in
NOTICE
README.md
pyproject.toml
requirements.txt
setup.py
object_database/Common.hpp
object_database/DatabaseConnectionPumpLoop.hpp
object_database/DatabaseConnectionState.hpp
object_database/DatabaseObject_test.py
object_database/DictInstance.hpp
object_database/HashFunctions.hpp
object_database/HashValue.hpp
object_database/IndexId.hpp
object_database/ObjectFieldId.hpp
object_database/PyDatabaseConnectionPumpLoop.cpp
object_database/PyDatabaseConnectionPumpLoop.hpp
object_database/PyDatabaseConnectionState.cpp
object_database/PyDatabaseConnectionState.hpp
object_database/PyDatabaseObjectType.cpp
object_database/PyDatabaseObjectType.hpp
object_database/PyVersionedIdSet.cpp
object_database/PyVersionedIdSet.hpp
object_database/PyView.cpp
object_database/PyView.hpp
object_database/RedisTestHelper.py
object_database/SchemaAndTypeName.hpp
object_database/VersionedIdSet.hpp
object_database/VersionedIdSet_test.py
object_database/VersionedObjects.hpp
object_database/VersionedObjectsOfMultiType.hpp
object_database/VersionedObjectsOfType.hpp
object_database/View.cpp
object_database/View.hpp
object_database/__init__.py
object_database/_types.cpp
object_database/all.cpp
object_database/bytecount_limited_queue.py
object_database/channel.py
object_database/core_schema.py
object_database/database_connection.py
object_database/database_connection_state_test.py
object_database/database_frontend_test.py
object_database/database_ring_invariant_test.py
object_database/database_test.py
object_database/identity.py
object_database/inmem_proxy_server.py
object_database/inmem_server.py
object_database/logging.yaml
object_database/message_bus.py
object_database/message_bus_test.py
object_database/messages.py
object_database/object.py
object_database/persistence.py
object_database/proxy_server.py
object_database/proxy_server_test.py
object_database/reactor.py
object_database/reactor_test.py
object_database/schema.py
object_database/server.py
object_database.egg-info/PKG-INFO
object_database.egg-info/SOURCES.txt
object_database.egg-info/dependency_links.txt
object_database.egg-info/entry_points.txt
object_database.egg-info/not-zip-safe
object_database.egg-info/requires.txt
object_database.egg-info/top_level.txt
