Metadata-Version: 1.1
Name: object-database
Version: 0.2
Summary: Distributed software transactional memory.
Home-page: https://github.com/aprioriinvestments/object_database
Author: Braxton Mckee
Author-email: braxton.mckee@gmail.com
License: Apache Software License v2.0
Platform: UNKNOWN
Classifier: License :: OSI Approved :: Apache Software License
Classifier: Programming Language :: Python :: 3 :: Only
